SimplerLLM/__init__.py
SimplerLLM/image/__init__.py
SimplerLLM/image/generation/__init__.py
SimplerLLM/image/generation/base.py
SimplerLLM/image/generation/providers/__init__.py
SimplerLLM/image/generation/providers/google_image.py
SimplerLLM/image/generation/providers/image_response_models.py
SimplerLLM/image/generation/providers/openai_image.py
SimplerLLM/image/generation/providers/seedream_image.py
SimplerLLM/image/generation/providers/stability_image.py
SimplerLLM/image/generation/wrappers/__init__.py
SimplerLLM/image/generation/wrappers/google_wrapper.py
SimplerLLM/image/generation/wrappers/openai_wrapper.py
SimplerLLM/image/generation/wrappers/seedream_wrapper.py
SimplerLLM/image/generation/wrappers/stability_wrapper.py
SimplerLLM/language/__init__.py
SimplerLLM/language/embeddings.py
SimplerLLM/language/llm_addons.py
SimplerLLM/language/flow/__init__.py
SimplerLLM/language/flow/flow.py
SimplerLLM/language/flow/models.py
SimplerLLM/language/flow/tool_registry.py
SimplerLLM/language/guardrails/__init__.py
SimplerLLM/language/guardrails/base.py
SimplerLLM/language/guardrails/exceptions.py
SimplerLLM/language/guardrails/wrapper.py
SimplerLLM/language/guardrails/input_guardrails/__init__.py
SimplerLLM/language/guardrails/input_guardrails/pii_detection.py
SimplerLLM/language/guardrails/input_guardrails/prompt_injection.py
SimplerLLM/language/guardrails/input_guardrails/topic_filter.py
SimplerLLM/language/guardrails/output_guardrails/__init__.py
SimplerLLM/language/guardrails/output_guardrails/content_safety.py
SimplerLLM/language/guardrails/output_guardrails/format_validator.py
SimplerLLM/language/guardrails/output_guardrails/length_validator.py
SimplerLLM/language/guardrails/output_guardrails/pii_detection.py
SimplerLLM/language/llm/__init__.py
SimplerLLM/language/llm/base.py
SimplerLLM/language/llm/reliable.py
SimplerLLM/language/llm/wrappers/__init__.py
SimplerLLM/language/llm/wrappers/anthropic_wrapper.py
SimplerLLM/language/llm/wrappers/cohere_wrapper.py
simplerllm-0.3.3.5.dist-info/licenses/LICENSE
simplerllm-0.3.3.5.dist-info/METADATA
simplerllm-0.3.3.5.dist-info/WHEEL
simplerllm-0.3.3.5.dist-info/top_level.txt
simplerllm-0.3.3.5.dist-info/RECORD
