Metadata-Version: 2.4
Name: SimplerLLM
Version: 0.3.3.5
Summary: An easy-to-use Library for interacting with language models.
Home-page: https://github.com/hassancs91/SimplerLLM
Author: Hasan Aboul Hasan
Author-email: hasan@learnwithhasan.com
License: MIT
Keywords: text generation,openai,LLM,RAG
Classifier: Development Status :: 4 - Beta
Classifier: Intended Audience :: Developers
Classifier: License :: OSI Approved :: MIT License
Classifier: Programming Language :: Python :: 3
Classifier: Programming Language :: Python :: 3.6
Classifier: Programming Language :: Python :: 3.7
Classifier: Programming Language :: Python :: 3.8
Classifier: Programming Language :: Python :: 3.9
Classifier: Programming Language :: Python :: 3.10
Classifier: Programming Language :: Python :: 3.11
Classifier: Programming Language :: Python :: 3.12
Classifier: Topic :: Software Development :: Libraries :: Python Modules
Requires-Python: >=3.6
License-File: LICENSE
Requires-Dist: aiohttp>=3.9
Requires-Dist: anthropic>=0.40.0
Requires-Dist: cohere>=5.0
Requires-Dist: duckduckgo_search>=5.3
Requires-Dist: elevenlabs>=1.0
Requires-Dist: lxml_html_clean>=0.1
Requires-Dist: newspaper3k>=0.2
Requires-Dist: numpy>=1.26
Requires-Dist: openai>=1.59
Requires-Dist: google-genai>=1.52.0
Requires-Dist: Pillow>=10.0
Requires-Dist: pydantic>=2.10
Requires-Dist: PyPDF2>=3.0
Requires-Dist: python-dotenv>=1.0
Requires-Dist: python_docx>=1.1
Requires-Dist: requests>=2.31
Requires-Dist: youtube_transcript_api>=0.6
Requires-Dist: colorama>=0.4
Requires-Dist: scipy>=1.15
Requires-Dist: tiktoken>=0.9
Requires-Dist: qdrant-client==1.14.3
Requires-Dist: voyageai==0.3.3
Requires-Dist: pydub>=0.25.1
Requires-Dist: elevenlabs>=2.22.0
Requires-Dist: moviepy>=1.0.3
Requires-Dist: yt-dlp>=2023.3.4
Provides-Extra: voice
Requires-Dist: pygame>=2.5.0; extra == "voice"
Requires-Dist: sounddevice>=0.4.6; extra == "voice"
Requires-Dist: pynput>=1.7.6; extra == "voice"
Provides-Extra: live-voice
Requires-Dist: sounddevice>=0.4.6; extra == "live-voice"
Requires-Dist: pynput>=1.7.6; extra == "live-voice"
Provides-Extra: all
Requires-Dist: pygame>=2.5.0; extra == "all"
Requires-Dist: sounddevice>=0.4.6; extra == "all"
Requires-Dist: pynput>=1.7.6; extra == "all"
Dynamic: author
Dynamic: author-email
Dynamic: classifier
Dynamic: description
Dynamic: description-content-type
Dynamic: home-page
Dynamic: keywords
Dynamic: license
Dynamic: license-file
Dynamic: provides-extra
Dynamic: requires-dist
Dynamic: requires-python
Dynamic: summary
